anemoi/datasets/__init__.py
anemoi/datasets/__main__.py
anemoi/datasets/_version.py
anemoi/datasets/grids.py
anemoi/datasets/commands/__init__.py
anemoi/datasets/commands/compare.py
anemoi/datasets/commands/copy.py
anemoi/datasets/commands/create.py
anemoi/datasets/commands/scan.py
anemoi/datasets/commands/inspect/__init__.py
anemoi/datasets/commands/inspect/zarr.py
anemoi/datasets/compute/perturbations.py
anemoi/datasets/create/__init__.py
anemoi/datasets/create/check.py
anemoi/datasets/create/chunks.py
anemoi/datasets/create/config.py
anemoi/datasets/create/input.py
anemoi/datasets/create/loaders.py
anemoi/datasets/create/patch.py
anemoi/datasets/create/persistent.py
anemoi/datasets/create/size.py
anemoi/datasets/create/template.py
anemoi/datasets/create/utils.py
anemoi/datasets/create/writer.py
anemoi/datasets/create/zarr.py
anemoi/datasets/create/functions/__init__.py
anemoi/datasets/create/functions/filters/__init__.py
anemoi/datasets/create/functions/filters/empty.py
anemoi/datasets/create/functions/filters/noop.py
anemoi/datasets/create/functions/filters/rename.py
anemoi/datasets/create/functions/filters/rotate_winds.py
anemoi/datasets/create/functions/filters/unrotate_winds.py
anemoi/datasets/create/functions/sources/__init__.py
anemoi/datasets/create/functions/sources/accumulations.py
anemoi/datasets/create/functions/sources/constants.py
anemoi/datasets/create/functions/sources/empty.py
anemoi/datasets/create/functions/sources/forcings.py
anemoi/datasets/create/functions/sources/grib.py
anemoi/datasets/create/functions/sources/mars.py
anemoi/datasets/create/functions/sources/netcdf.py
anemoi/datasets/create/functions/sources/opendap.py
anemoi/datasets/create/functions/sources/perturbations.py
anemoi/datasets/create/functions/sources/source.py
anemoi/datasets/create/functions/sources/tendencies.py
anemoi/datasets/create/statistics/__init__.py
anemoi/datasets/create/statistics/summary.py
anemoi/datasets/data/__init__.py
anemoi/datasets/data/concat.py
anemoi_dataset-0.1.5.dist-info/LICENSE
anemoi_dataset-0.1.5.dist-info/METADATA
anemoi_dataset-0.1.5.dist-info/WHEEL
anemoi_dataset-0.1.5.dist-info/entry_points.txt
anemoi_dataset-0.1.5.dist-info/top_level.txt
anemoi_dataset-0.1.5.dist-info/RECORD
