Metadata-Version: 2.1
Name: anemoi-dataset
Version: 0.1.5
Summary: A package to hold various functions to support training of ML models on ECMWF data.
Author-email: "European Centre for Medium-Range Weather Forecasts (ECMWF)" <software.support@ecmwf.int>
License: Apache License
Project-URL: Homepage, https://github.com/ecmwf/anemoi-datasets/
Project-URL: Documentation, https://anemoi-datasets.readthedocs.io/
Project-URL: Repository, https://github.com/ecmwf/anemoi-datasets/
Project-URL: Issues, https://github.com/ecmwf/anemoi-datasets/issues
Keywords: tools,datasets,ai
Classifier: Development Status :: 4 - Beta
Classifier: Intended Audience :: Developers
Classifier: License :: OSI Approved :: Apache Software License
Classifier: Programming Language :: Python :: 3
Classifier: Programming Language :: Python :: 3.9
Classifier: Programming Language :: Python :: 3.10
Classifier: Programming Language :: Python :: 3.11
Classifier: Programming Language :: Python :: Implementation :: CPython
Classifier: Programming Language :: Python :: Implementation :: PyPy
Classifier: Operating System :: OS Independent
Requires-Python: >=3.9
License-File: LICENSE
Requires-Dist: anemoi-utils[provenance] >=0.1.7
Requires-Dist: zarr
Requires-Dist: pyyaml
Requires-Dist: numpy
Requires-Dist: tqdm
Requires-Dist: semantic-version
Provides-Extra: all
Requires-Dist: boto3 ; extra == 'all'
Requires-Dist: requests ; extra == 'all'
Requires-Dist: s3fs ; extra == 'all'
Requires-Dist: climetlab >=0.22.1 ; extra == 'all'
Requires-Dist: earthkit-meteo ; extra == 'all'
Requires-Dist: pyproj ; extra == 'all'
Requires-Dist: ecmwflibs >=0.6.3 ; extra == 'all'
Provides-Extra: create
Requires-Dist: climetlab >=0.22.1 ; extra == 'create'
Requires-Dist: earthkit-meteo ; extra == 'create'
Requires-Dist: pyproj ; extra == 'create'
Requires-Dist: ecmwflibs >=0.6.3 ; extra == 'create'
Provides-Extra: dev
Requires-Dist: boto3 ; extra == 'dev'
Requires-Dist: requests ; extra == 'dev'
Requires-Dist: s3fs ; extra == 'dev'
Requires-Dist: climetlab >=0.22.1 ; extra == 'dev'
Requires-Dist: earthkit-meteo ; extra == 'dev'
Requires-Dist: pyproj ; extra == 'dev'
Requires-Dist: ecmwflibs >=0.6.3 ; extra == 'dev'
Requires-Dist: sphinx ; extra == 'dev'
Requires-Dist: sphinx-rtd-theme ; extra == 'dev'
Requires-Dist: nbsphinx ; extra == 'dev'
Requires-Dist: pandoc ; extra == 'dev'
Provides-Extra: docs
Requires-Dist: sphinx ; extra == 'docs'
Requires-Dist: sphinx-rtd-theme ; extra == 'docs'
Requires-Dist: nbsphinx ; extra == 'docs'
Requires-Dist: pandoc ; extra == 'docs'
Provides-Extra: remote
Requires-Dist: boto3 ; extra == 'remote'
Requires-Dist: requests ; extra == 'remote'
Requires-Dist: s3fs ; extra == 'remote'
